asynctelegraf/__init__.py
asynctelegraf/client.py
asynctelegraf/protocol.py
asynctelegraf/types.py
asynctelegraf/utils.py
asynctelegraf/version.py
tests/__init__.py
tests/conftest.py
tests/helpers.py
tests/test_metrics.py
tests/test_performance.py
tests/test_protocol.py
tests/test_sender.py
asynctelegraf-1.0.1.dist-info/LICENSE
asynctelegraf-1.0.1.dist-info/METADATA
asynctelegraf-1.0.1.dist-info/WHEEL
asynctelegraf-1.0.1.dist-info/top_level.txt
asynctelegraf-1.0.1.dist-info/RECORD
