Metadata-Version: 2.1
Name: asynctelegraf
Version: 1.0.1
Summary: asyncio python client for telegraf / statsd / AWD cloudwatch
Home-page: https://github.com/mastak/asynctelegraf
Author: Ihor Liubymov
Author-email: infunt@gmail.com
License: UNKNOWN
Platform: UNKNOWN
Requires-Python: >=3.7
License-File: LICENSE
